Classfile /Users/adian/Desktop/research/cov-demo/ignore/edu/nju/isefuzz/HelloBranches.class
  Last modified 2023年10月7日; size 1258 bytes
  MD5 checksum b84ece8d132243e4da44355565c66ae5
  Compiled from "HelloBranches.java"
public class edu.nju.isefuzz.HelloBranches
  minor version: 0
  major version: 55
  flags: (0x0001) ACC_PUBLIC
  this_class: #2                          // edu/nju/isefuzz/HelloBranches
  super_class: #4                         // java/lang/Object
  interfaces: 0, fields: 0, methods: 3, attributes: 1
Constant pool:
   #1 = Utf8               edu/nju/isefuzz/HelloBranches
   #2 = Class              #1             // edu/nju/isefuzz/HelloBranches
   #3 = Utf8               java/lang/Object
   #4 = Class              #3             // java/lang/Object
   #5 = Utf8               HelloBranches.java
   #6 = Utf8               <init>
   #7 = Utf8               ()V
   #8 = NameAndType        #6:#7          // "<init>":()V
   #9 = Methodref          #4.#8          // java/lang/Object."<init>":()V
  #10 = Utf8               this
  #11 = Utf8               Ledu/nju/isefuzz/HelloBranches;
  #12 = Utf8               main
  #13 = Utf8               ([Ljava/lang/String;)V
  #14 = Utf8               printCov
  #15 = NameAndType        #14:#7         // printCov:()V
  #16 = Methodref          #2.#15         // edu/nju/isefuzz/HelloBranches.printCov:()V
  #17 = Utf8               java/lang/System
  #18 = Class              #17            // java/lang/System
  #19 = Utf8               out
  #20 = Utf8               Ljava/io/PrintStream;
  #21 = NameAndType        #19:#20        // out:Ljava/io/PrintStream;
  #22 = Fieldref           #18.#21        // java/lang/System.out:Ljava/io/PrintStream;
  #23 = Utf8               Require 1 arg!!!
  #24 = String             #23            // Require 1 arg!!!
  #25 = Utf8               java/io/PrintStream
  #26 = Class              #25            // java/io/PrintStream
  #27 = Utf8               println
  #28 = Utf8               (Ljava/lang/String;)V
  #29 = NameAndType        #27:#28        // println:(Ljava/lang/String;)V
  #30 = Methodref          #26.#29        // java/io/PrintStream.println:(Ljava/lang/String;)V
  #31 = Utf8               exit
  #32 = Utf8               (I)V
  #33 = NameAndType        #31:#32        // exit:(I)V
  #34 = Methodref          #18.#33        // java/lang/System.exit:(I)V
  #35 = Utf8               java/lang/String
  #36 = Class              #35            // java/lang/String
  #37 = Utf8               toCharArray
  #38 = Utf8               ()[C
  #39 = NameAndType        #37:#38        // toCharArray:()[C
  #40 = Methodref          #36.#39        // java/lang/String.toCharArray:()[C
  #41 = Utf8               Catch h!
  #42 = String             #41            // Catch h!
  #43 = Utf8               Catch he!
  #44 = String             #43            // Catch he!
  #45 = Utf8               Catch hel!
  #46 = String             #45            // Catch hel!
  #47 = Utf8               Catch hell!
  #48 = String             #47            // Catch hell!
  #49 = Utf8               Catch hello!
  #50 = String             #49            // Catch hello!
  #51 = Utf8               [C
  #52 = Class              #51            // "[C"
  #53 = Utf8               Failed at (4, o)!
  #54 = String             #53            // Failed at (4, o)!
  #55 = Utf8               Failed at (3, l)!
  #56 = String             #55            // Failed at (3, l)!
  #57 = Utf8               Failed at (2, l)!
  #58 = String             #57            // Failed at (2, l)!
  #59 = Utf8               Failed at (1, e)!
  #60 = String             #59            // Failed at (1, e)!
  #61 = Utf8               Failed at (0, h)!
  #62 = String             #61            // Failed at (0, h)!
  #63 = Utf8               args
  #64 = Utf8               [Ljava/lang/String;
  #65 = Utf8               charArr
  #66 = Utf8               [LOG] Reaching a branch!
  #67 = String             #66            // [LOG] Reaching a branch!
  #68 = Utf8               Code
  #69 = Utf8               LineNumberTable
  #70 = Utf8               LocalVariableTable
  #71 = Utf8               StackMapTable
  #72 = Utf8               SourceFile
{
  public edu.nju.isefuzz.HelloBranches();
    descriptor: ()V
    flags: (0x0001) ACC_PUBLIC
    Code:
      stack=1, locals=1, args_size=1
         0: aload_0
         1: invokespecial #9                  // Method java/lang/Object."<init>":()V
         4: return
      LineNumberTable:
        line 3: 0
      LocalVariableTable:
        Start  Length  Slot  Name   Signature
            0       5     0  this   Ledu/nju/isefuzz/HelloBranches;

  public static void main(java.lang.String[]);
    descriptor: ([Ljava/lang/String;)V
    flags: (0x0009) ACC_PUBLIC, ACC_STATIC
    Code:
      stack=2, locals=2, args_size=1
         0: aload_0
         1: arraylength
         2: iconst_1
         3: if_icmpeq     21
         6: invokestatic  #16                 // Method printCov:()V
         9: getstatic     #22                 // Field java/lang/System.out:Ljava/io/PrintStream;
        12: ldc           #24                 // String Require 1 arg!!!
        14: invokevirtual #30                 // Method java/io/PrintStream.println:(Ljava/lang/String;)V
        17: iconst_0
        18: invokestatic  #34                 // Method java/lang/System.exit:(I)V
        21: aload_0
        22: iconst_0
        23: aaload
        24: invokevirtual #40                 // Method java/lang/String.toCharArray:()[C
        27: astore_1
        28: aload_1
        29: iconst_0
        30: caload
        31: bipush        104
        33: if_icmpne     185
        36: invokestatic  #16                 // Method printCov:()V
        39: getstatic     #22                 // Field java/lang/System.out:Ljava/io/PrintStream;
        42: ldc           #42                 // String Catch h!
        44: invokevirtual #30                 // Method java/io/PrintStream.println:(Ljava/lang/String;)V
        47: aload_1
        48: iconst_1
        49: caload
        50: bipush        101
        52: if_icmpne     171
        55: invokestatic  #16                 // Method printCov:()V
        58: getstatic     #22                 // Field java/lang/System.out:Ljava/io/PrintStream;
        61: ldc           #44                 // String Catch he!
        63: invokevirtual #30                 // Method java/io/PrintStream.println:(Ljava/lang/String;)V
        66: aload_1
        67: iconst_2
        68: caload
        69: bipush        108
        71: if_icmpne     157
        74: invokestatic  #16                 // Method printCov:()V
        77: getstatic     #22                 // Field java/lang/System.out:Ljava/io/PrintStream;
        80: ldc           #46                 // String Catch hel!
        82: invokevirtual #30                 // Method java/io/PrintStream.println:(Ljava/lang/String;)V
        85: aload_1
        86: iconst_3
        87: caload
        88: bipush        108
        90: if_icmpne     143
        93: invokestatic  #16                 // Method printCov:()V
        96: getstatic     #22                 // Field java/lang/System.out:Ljava/io/PrintStream;
        99: ldc           #48                 // String Catch hell!
       101: invokevirtual #30                 // Method java/io/PrintStream.println:(Ljava/lang/String;)V
       104: aload_1
       105: iconst_4
       106: caload
       107: bipush        111
       109: if_icmpne     129
       112: invokestatic  #16                 // Method printCov:()V
       115: getstatic     #22                 // Field java/lang/System.out:Ljava/io/PrintStream;
       118: ldc           #50                 // String Catch hello!
       120: invokevirtual #30                 // Method java/io/PrintStream.println:(Ljava/lang/String;)V
       123: goto          193
       126: invokestatic  #16                 // Method printCov:()V
       129: getstatic     #22                 // Field java/lang/System.out:Ljava/io/PrintStream;
       132: ldc           #54                 // String Failed at (4, o)!
       134: invokevirtual #30                 // Method java/io/PrintStream.println:(Ljava/lang/String;)V
       137: goto          193
       140: invokestatic  #16                 // Method printCov:()V
       143: getstatic     #22                 // Field java/lang/System.out:Ljava/io/PrintStream;
       146: ldc           #56                 // String Failed at (3, l)!
       148: invokevirtual #30                 // Method java/io/PrintStream.println:(Ljava/lang/String;)V
       151: goto          193
       154: invokestatic  #16                 // Method printCov:()V
       157: getstatic     #22                 // Field java/lang/System.out:Ljava/io/PrintStream;
       160: ldc           #58                 // String Failed at (2, l)!
       162: invokevirtual #30                 // Method java/io/PrintStream.println:(Ljava/lang/String;)V
       165: goto          193
       168: invokestatic  #16                 // Method printCov:()V
       171: getstatic     #22                 // Field java/lang/System.out:Ljava/io/PrintStream;
       174: ldc           #60                 // String Failed at (1, e)!
       176: invokevirtual #30                 // Method java/io/PrintStream.println:(Ljava/lang/String;)V
       179: goto          193
       182: invokestatic  #16                 // Method printCov:()V
       185: getstatic     #22                 // Field java/lang/System.out:Ljava/io/PrintStream;
       188: ldc           #62                 // String Failed at (0, h)!
       190: invokevirtual #30                 // Method java/io/PrintStream.println:(Ljava/lang/String;)V
       193: return
      StackMapTable: number_of_entries = 7
        frame_type = 21 /* same */
        frame_type = 252 /* append */
          offset_delta = 107
          locals = [ class "[C" ]
        frame_type = 13 /* same */
        frame_type = 13 /* same */
        frame_type = 13 /* same */
        frame_type = 13 /* same */
        frame_type = 7 /* same */
      LineNumberTable:
        line 7: 0
        line 8: 9
        line 9: 17
        line 13: 21
        line 14: 28
        line 15: 39
        line 16: 47
        line 17: 58
        line 18: 66
        line 19: 77
        line 20: 85
        line 21: 96
        line 22: 104
        line 23: 115
        line 25: 129
        line 27: 143
        line 30: 157
        line 33: 171
        line 36: 185
        line 39: 193
      LocalVariableTable:
        Start  Length  Slot  Name   Signature
            0     194     0  args   [Ljava/lang/String;
           28     166     1 charArr   [C

  public static void printCov();
    descriptor: ()V
    flags: (0x0009) ACC_PUBLIC, ACC_STATIC
    Code:
      stack=2, locals=0, args_size=0
         0: getstatic     #22                 // Field java/lang/System.out:Ljava/io/PrintStream;
         3: ldc           #67                 // String [LOG] Reaching a branch!
         5: invokevirtual #30                 // Method java/io/PrintStream.println:(Ljava/lang/String;)V
         8: return
}
SourceFile: "HelloBranches.java"
